qipu/__init__.py
qipu/__version__.py
qipu-0.1.0a1.dist-info/METADATA
qipu-0.1.0a1.dist-info/RECORD
qipu-0.1.0a1.dist-info/WHEEL
qipu-0.1.0a1.dist-info/entry_points.txt
qipu-0.1.0a1.dist-info/top_level.txt
